.gitignore
MANIFEST.in
README.rst
bootstrap.py
buildout.cfg
setup.py
collective/__init__.py
collective.portlet.jqueryuicalendar.egg-info/PKG-INFO
collective.portlet.jqueryuicalendar.egg-info/SOURCES.txt
collective.portlet.jqueryuicalendar.egg-info/dependency_links.txt
collective.portlet.jqueryuicalendar.egg-info/entry_points.txt
collective.portlet.jqueryuicalendar.egg-info/namespace_packages.txt
collective.portlet.jqueryuicalendar.egg-info/not-zip-safe
collective.portlet.jqueryuicalendar.egg-info/requires.txt
collective.portlet.jqueryuicalendar.egg-info/top_level.txt
collective/portlet/__init__.py
collective/portlet/jqueryuicalendar/__init__.py
collective/portlet/jqueryuicalendar/configure.zcml
collective/portlet/jqueryuicalendar/jqueryuicalendarportlet.css
collective/portlet/jqueryuicalendar/jqueryuicalendarportlet.js
collective/portlet/jqueryuicalendar/jqueryuicalendarportlet.pt
collective/portlet/jqueryuicalendar/jqueryuicalendarportlet.py
collective/portlet/jqueryuicalendar/upgrades.py
collective/portlet/jqueryuicalendar/upgrades.zcml
collective/portlet/jqueryuicalendar/version.txt
collective/portlet/jqueryuicalendar/profiles/default/cssregistry.xml
collective/portlet/jqueryuicalendar/profiles/default/jsregistry.xml
collective/portlet/jqueryuicalendar/profiles/default/metadata.xml
collective/portlet/jqueryuicalendar/profiles/default/portlets.xml
collective/portlet/jqueryuicalendar/tests/__init__.py
collective/portlet/jqueryuicalendar/tests/base.py
collective/portlet/jqueryuicalendar/tests/test_portlet.py
docs/HISTORY.txt
docs/INSTALL.txt
docs/LICENSE.GPL
docs/LICENSE.txt