Metadata-Version: 1.0
Name: collective.portlet.jqueryuicalendar
Version: 0.1
Summary: jQueryUI Calendar portlet to replace stock Plone calendar portlet
Home-page: https://github.com/collective/collective.portlet.jqueryuicalendar
Author: JeanMichel FRANCOIS aka toutpt
Author-email: toutpt@gmail.com
License: GPL
Keywords: plone
Platform: UNKNOWN
Classifier: Framework :: Plone
Classifier: Programming Language :: Python
